eccLib.cpython-310-i386-linux-gnu.so
eccLib/__init__.pyi
ecclib-1.1.0.dist-info/METADATA
ecclib-1.1.0.dist-info/WHEEL
ecclib-1.1.0.dist-info/top_level.txt
ecclib-1.1.0.dist-info/RECORD
ecclib-1.1.0.dist-info/licenses/LICENSE.txt
